{
  "app": {
    "name": "Bookz Doctor",
    "host": "18.209.171.143",
    "port": 8080,
    "jwtAlgo": "HS512",
    "jwtKey": "bookzdoctor",
    "webUrl": "https://bookzdoctor.com",
    "apiHost": "18.209.171.143"
  },
  "db": {
    "name": "bookzdoctor",
    "host": "18.209.171.143",
    "auth": true,
    "username": "bookzdoctor",
    "password": "bookzdoctors456",
    "port": 27017,
    "mongoose": {
      "useMongoClient": true,
      "autoIndex": true, // Don't build indexes
      "poolSize": 10, // Maintain up to 10 socket connections
      // If not connected, return errors immediately rather than waiting for reconnect
      "bufferMaxEntries": 0
    }
  },
  "smtp": {
    "smtpUser": "support@bookzdoctor.com",
    "smtpPass": "BookzDoctor1989!",
    "smtpPort": 587, //25,
    "smtpServer": "smtpout.secureserver.net",
    "mailFrom": "support@bookzdoctor.com"
  },
  "stripe": {
    //"secretKey": "sk_test_51GusRiIlbP5wS7hwUUCPUUWyTSMJuE748fwA1OktWuJRLBX5LJsx0qMnFsJzGC3Rn7SOvHjsser5RGTLXQS871jt00LgMrjc5q", //"sk_test_6BSWQwmxu1OlJmldUy3uLHNJ00n9eQXzfX",
    //"publicKey": "pk_test_51GusRiIlbP5wS7hwGUsvDIwygVrL3m7xQpNCxpVOVCnpytemwDs6Kl5BM0UUb657UC7wiAwfpcB9iUHf2tn8cgGH00Wdg0QRVw",
    "secretKey": "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", //"sk_test_6BSWQwmxu1OlJmldUy3uLHNJ00n9eQXzfX",
    "publicKey": "pk_live_51GxBM5FTMzJ0yhP1OWbbvnYVR9xowKtAb9DOQaJo7mawmbMRwHXYMSJMRQBKFNykydL4y6fp64ulI211E8ATODXN00A5ESNNez",
    "serviceTax" : 2,
    "commisionFromDoctor" : 5,
    "commisionFromPatient": 10
  },
  "apn": {
    "keyId": "CKSJQFW5LZ",
    "teamId": "56SX64P5F6",
    "appTitle": "Bookzdoctor"
  },
  "ios": {
    "cert": "",
    "key": "",
    "gateway": "gateway.sandbox.push.apple.com",
    "production": true
  }
}


